MANIFEST.in
README.rst
setup.cfg
setup.py
tox.ini
after_deploy/__init__.py
after_deploy/after_deploy.py
after_deploy/apps.py
after_deploy/models.py
after_deploy/tests.py
after_deploy/management/__init__.py
after_deploy/management/commands/__init__.py
after_deploy/management/commands/after_deploy.py
after_deploy/migrations/0001_initial.py
after_deploy/migrations/__init__.py
django_after_deploy.egg-info/PKG-INFO
django_after_deploy.egg-info/SOURCES.txt
django_after_deploy.egg-info/dependency_links.txt
django_after_deploy.egg-info/not-zip-safe
django_after_deploy.egg-info/requires.txt
django_after_deploy.egg-info/top_level.txt