Metadata-Version: 1.2
Name: django-after-deploy
Version: 0.0.1
Summary: Automated tasks after-deploy for Django.
Home-page: https://github.com/dfop02/django-after-deploy
Author: Diogo Fernandes
Author-email: dfop02@hotmail.com
License: MIT
Project-URL: Source, https://github.com/dfop02/django-after-deploy
Keywords: django,task,tasks
Platform: any
Classifier: Programming Language :: Python :: 3
Classifier: License :: OSI Approved :: MIT License
Requires-Python: >=3.6
